virtualenvwrapper.basic-0.2.1-py3.5-nspkg.pth
virtualenvwrapper/basic_project.py
virtualenvwrapper/__pycache__/basic_project.cpython-35.pyc
virtualenvwrapper/basic.skel/ANNOUNCE
virtualenvwrapper/basic.skel/AUTHORS
virtualenvwrapper/basic.skel/CHANGES
virtualenvwrapper/basic.skel/LICENSE
virtualenvwrapper/basic.skel/MANIFEST.in
virtualenvwrapper/basic.skel/README.rst
virtualenvwrapper/basic.skel/requirements.txt
virtualenvwrapper/basic.skel/requirements_test.txt
virtualenvwrapper/basic.skel/setup.$$
virtualenvwrapper/basic.skel/$PROJECT_NAME/__init__.$$
virtualenvwrapper.basic-0.2.1.dist-info/DESCRIPTION.rst
virtualenvwrapper.basic-0.2.1.dist-info/METADATA
virtualenvwrapper.basic-0.2.1.dist-info/RECORD
virtualenvwrapper.basic-0.2.1.dist-info/WHEEL
virtualenvwrapper.basic-0.2.1.dist-info/entry_points.txt
virtualenvwrapper.basic-0.2.1.dist-info/metadata.json
virtualenvwrapper.basic-0.2.1.dist-info/namespace_packages.txt
virtualenvwrapper.basic-0.2.1.dist-info/top_level.txt
