Metadata-Version: 2.0
Name: virtualenvwrapper.basic
Version: 0.2.1
Summary: A Python application template for virtualenvwrapper.
Home-page: https://github.com/morgan-del/virtualenwrapper.basic
Author: Morgan Delahaye-Prat
Author-email: mdp@sillog.net
License: BSD
Platform: Any
Classifier: Development Status :: 3 - Alpha
Classifier: License :: OSI Approved :: BSD License
Classifier: Intended Audience :: Developers
Classifier: Environment :: Console
Classifier: Programming Language :: Python :: 2
Classifier: Programming Language :: Python :: 2.6
Classifier: Programming Language :: Python :: 2.7
Classifier: Programming Language :: Python :: 3
Classifier: Programming Language :: Python :: 3.2
Classifier: Programming Language :: Python :: 3.3
Classifier: Programming Language :: Python :: 3.4
Classifier: Programming Language :: Python :: 3.5
Requires: virtualenv
Requires: virtualenvwrapper (>=4.0)
